{"id":"index.html","dependencies":[{"name":"/Users/wangdanmeng/Documents/前端/饥人谷/6 MVC/mvc-demo-1/package.json","includedInParent":true,"mtime":1671025945941},{"name":"./main.js","dynamic":true,"parent":"/Users/wangdanmeng/Documents/前端/饥人谷/6 MVC/mvc-demo-1/src/index.html","resolved":"/Users/wangdanmeng/Documents/前端/饥人谷/6 MVC/mvc-demo-1/src/main.js"}],"generated":{"html":"<!DOCTYPE html>\n<html lang=\"en\">\n\n<head>\n  <meta charset=\"UTF-8\">\n  <meta http-equiv=\"X-UA-Compatible\" content=\"IE=edge\">\n  <meta name=\"viewport\" content=\"width=device-width,initial-scale=1,minimum-scale=1,maximum-scale=1,user-scalable=no,viewport-fit=cover\">\n  <title>MVC demo</title>\n</head>\n\n<body>\n  <div class=\"container\">\n    <section class=\"app app1\">\n      <div class=\"result\">计算结果: <span id=\"resultNum\">1</span></div>\n      <button class=\"btn add\">加1</button>\n      <button class=\"btn sub\">减1</button>\n      <button class=\"btn mul\">乘2</button>\n      <button class=\"btn div\">除2</button>\n    </section>\n    <section class=\"app app2\">\n      <ol class=\"tab-bar\">\n        <li class=\"tab1 \">tab1</li>\n        <li class=\"tab2\">tab2</li>\n      </ol>\n      <ol class=\"tab-content\">\n        <li class=\"active\">content1</li>\n        <li>content2</li>\n      </ol>\n    </section>\n    <section class=\"app app3\">\n      鼠标点击,方块移动\n      <div class=\"box\"></div>\n    </section>\n    <section class=\"app app4\">\n      点击小球,实现渐变\n      <div class=\"circle\"></div>\n    </section>\n  </div>\n\n  <script src=\"/aa7b7f029cd03854c2f2bbdcf5c14154.js\"></script>\n</body>\n\n</html>"},"hash":"8f85473e0a2ccef46006e4b6b42273f7","cacheData":{}}